privacy_ccp/__init__.py
privacy_ccp/communication_system/__init__.py
privacy_ccp/communication_system/message.py
privacy_ccp/communication_system/message_board.py
privacy_ccp/crypto/__init__.py
privacy_ccp/crypto/dsa_encryption.py
privacy_ccp/crypto/encryption.py
privacy_ccp/crypto/generate_hash.py
privacy_ccp/crypto/generate_signature.py
privacy_ccp/crypto/rsa_encryption.py
privacy_ccp/main.py
privacy_ccp/privacy_contracts/__init__.py
privacy_ccp/simulation_environment/__init__.py
privacy_ccp/simulation_environment/user_agent.py
privacy_ccp-0.1.1.dist-info/entry_points.txt
privacy_ccp-0.1.1.dist-info/WHEEL
privacy_ccp-0.1.1.dist-info/METADATA
privacy_ccp-0.1.1.dist-info/RECORD
