Metadata-Version: 2.1
Name: privacy-ccp
Version: 0.1.1
Summary: Privacy Preserving Collective Computation Platform
License: MIT
Author: Pradipta Deb
Author-email: pradipta.deb@inria.fr
Requires-Python: >=3.7,<4.0
Classifier: License :: OSI Approved :: MIT License
Classifier: Programming Language :: Python :: 3
Classifier: Programming Language :: Python :: 3.7
Classifier: Programming Language :: Python :: 3.8
Requires-Dist: click (>=7.0,<8.0)
Requires-Dist: pycryptodome (>=3.9.4,<4.0.0)
Requires-Dist: tqdm (>=4.42.0,<5.0.0)
